CHANGES.txt
README.txt
bootstrap.py
buildout.cfg
setup.py
src/hurry/__init__.py
src/hurry.jgrowl.egg-info/PKG-INFO
src/hurry.jgrowl.egg-info/SOURCES.txt
src/hurry.jgrowl.egg-info/dependency_links.txt
src/hurry.jgrowl.egg-info/entry_points.txt
src/hurry.jgrowl.egg-info/namespace_packages.txt
src/hurry.jgrowl.egg-info/not-zip-safe
src/hurry.jgrowl.egg-info/requires.txt
src/hurry.jgrowl.egg-info/top_level.txt
src/hurry/jgrowl/__init__.py
src/hurry/jgrowl/jgrowl.txt
src/hurry/jgrowl/tests.py
src/hurry/jgrowl/jgrowl-build/jquery.jgrowl.css
src/hurry/jgrowl/jgrowl-build/jquery.jgrowl.js
src/hurry/jgrowl/jgrowl-build/jquery.jgrowl_compressed.js
src/hurry/jgrowl/jgrowl-build/jquery.jgrowl_minimized.js