Metadata-Version: 1.0
Name: hurry.jgrowl
Version: 1.2.4
Summary: UNKNOWN
Home-page: UNKNOWN
Author: Martijn Faassen / Izhar Firdaus
Author-email: faassen@startifact.com
License: MIT
Platform: UNKNOWN
Classifier: Programming Language :: Python
